LICENSE
MANIFEST.in
README.md
setup.py
django_markdown_filter.egg-info/PKG-INFO
django_markdown_filter.egg-info/SOURCES.txt
django_markdown_filter.egg-info/dependency_links.txt
django_markdown_filter.egg-info/requires.txt
django_markdown_filter.egg-info/top_level.txt
markdown_filter/__init__.py
markdown_filter/templatetags/__init__.py
markdown_filter/templatetags/markdown_filter.py