Metadata-Version: 1.1
Name: django-markdown-filter
Version: 0.0.1
Summary: Markdown template filter for Django.
Home-page: https://github.com/mrtc0/django-markdown-filter
Author: mrtc0
Author-email: mrtc0.py@gmail.com
License: MIT
Platform: UNKNOWN
Classifier: Framework :: Django
